manage_fastapi/__init__.py
manage_fastapi/__main__.py
manage_fastapi/config.py
manage_fastapi/constants.py
manage_fastapi/context.py
manage_fastapi/generator.py
manage_fastapi/helpers.py
manage_fastapi/main.py
manage_fastapi/templates/__init__.py
manage_fastapi/templates/app/__init__.py
manage_fastapi/templates/app/cookiecutter.json
manage_fastapi/templates/app/hooks/post_gen_project.py
manage_fastapi/templates/app/{{ cookiecutter.folder_name }}/__init__.py
manage_fastapi/templates/app/{{ cookiecutter.folder_name }}/api/__init__.py
manage_fastapi/templates/app/{{ cookiecutter.folder_name }}/api/v1.py
manage_fastapi/templates/app/{{ cookiecutter.folder_name }}/crud.py
manage_fastapi/templates/app/{{ cookiecutter.folder_name }}/models.py
manage_fastapi/templates/app/{{ cookiecutter.folder_name }}/schemas.py
manage_fastapi/templates/project/__init__.py
manage_fastapi/templates/project/cookiecutter.json
manage_fastapi/templates/project/hooks/post_gen_project.py
manage_fastapi/templates/project/{{ cookiecutter.folder_name }}/.pre-commit-config.yaml
manage_fastapi/templates/project/{{ cookiecutter.folder_name }}/Dockerfile
manage_fastapi/templates/project/{{ cookiecutter.folder_name }}/LICENSE
manage_fastapi/templates/project/{{ cookiecutter.folder_name }}/README.md
manage_fastapi/templates/project/{{ cookiecutter.folder_name }}/app/__init__.py
manage_fastapi/templates/project/{{ cookiecutter.folder_name }}/app/core/__init__.py
manage_fastapi/templates/project/{{ cookiecutter.folder_name }}/app/core/config.py
manage_fastapi/templates/project/{{ cookiecutter.folder_name }}/app/database.py
manage_fastapi/templates/project/{{ cookiecutter.folder_name }}/app/main.py
manage_fastapi/templates/project/{{ cookiecutter.folder_name }}/docker-compose.yaml
manage_fastapi/templates/project/{{ cookiecutter.folder_name }}/pyproject.toml
manage_fastapi/templates/project/{{ cookiecutter.folder_name }}/requirements.txt
manage_fastapi-1.1.0.dist-info/entry_points.txt
manage_fastapi-1.1.0.dist-info/LICENSE
manage_fastapi-1.1.0.dist-info/WHEEL
manage_fastapi-1.1.0.dist-info/METADATA
manage_fastapi-1.1.0.dist-info/RECORD
