Metadata-Version: 2.1
Name: manage-fastapi
Version: 1.1.0
Summary: Managing FastAPI projects made easy.
Home-page: https://github.com/ycd/manage-fastapi
License: MIT
Author: ycd
Author-email: yagizcanilbey1903@gmail.com
Requires-Python: >=3.6.1,<4.0.0
Classifier: Intended Audience :: Developers
Classifier: License :: OSI Approved :: MIT License
Classifier: Operating System :: OS Independent
Classifier: Programming Language :: Python
Classifier: Programming Language :: Python :: 3
Classifier: Programming Language :: Python :: 3 :: Only
Classifier: Programming Language :: Python :: 3.6
Classifier: Programming Language :: Python :: 3.7
Classifier: Programming Language :: Python :: 3.8
Classifier: Programming Language :: Python :: 3.9
Classifier: Topic :: Software Development :: Build Tools
Classifier: Topic :: Software Development :: Libraries :: Python Modules
Requires-Dist: cookiecutter (>=1.7.2,<2.0.0)
Requires-Dist: pydantic[email] (>=1.7.2,<2.0.0)
Requires-Dist: questionary (>=1.10.0,<2.0.0)
Requires-Dist: typer (>=0.4.0,<0.5.0)
Project-URL: Repository, https://github.com/ycd/manage-fastapi
